colemen_time_utils.py
build_utils/__init__.py
build_utils/build_package.py
build_utils/general.py
colemen_time_utilities/__init__.py
colemen_time_utilities/convert.py
colemen_time_utilities/current.py
colemen_time_utils-0.0.0.dist-info/METADATA
colemen_time_utils-0.0.0.dist-info/WHEEL
colemen_time_utils-0.0.0.dist-info/top_level.txt
colemen_time_utils-0.0.0.dist-info/RECORD
